custom_neural_net_creator/__init__.py
custom_neural_net_creator/activation_functions.py
custom_neural_net_creator/activation_layer.py
custom_neural_net_creator/dense.py
custom_neural_net_creator/loss_functions.py
custom_neural_net_creator/model.py
custom_neural_net_creator-2.0.dist-info/METADATA
custom_neural_net_creator-2.0.dist-info/WHEEL
custom_neural_net_creator-2.0.dist-info/top_level.txt
custom_neural_net_creator-2.0.dist-info/RECORD
