Metadata-Version: 2.1
Name: custom-neural-net-creator
Version: 2.0
Summary: A Neural Network Module to create Custom Dense Neural Networks
Author: Yogesh Seenichamy
Author-email: yogeshseeni60@gmail.com
License: MIT
Project-URL: Homepage, https://github.com/YogeshSeeni/NeuralNetworkModule
Project-URL: Documentation, https://custom-neural-net-creator.readthedocs.io/en/latest/
Classifier: Programming Language :: Python :: 3
Classifier: License :: OSI Approved :: MIT License
Classifier: Operating System :: OS Independent
Requires-Dist: numpy
